a_cv2_shape_finder/LICENSE
a_cv2_shape_finder/README.MD
a_cv2_shape_finder/__init__.py
a_cv2_shape_finder/requirements.txt
a_cv2_shape_finder/thirdparty.json
a_cv2_shape_finder-0.11.dist-info/LICENSE.rst
a_cv2_shape_finder-0.11.dist-info/METADATA
a_cv2_shape_finder-0.11.dist-info/WHEEL
a_cv2_shape_finder-0.11.dist-info/top_level.txt
a_cv2_shape_finder-0.11.dist-info/RECORD
