Metadata-Version: 2.1
Name: a-cv2-shape-finder
Version: 0.11
Summary: Detecting shapes with OpenCV, and getting all the important information in a DataFrame
Home-page: https://github.com/hansalemaos/a_cv2_shape_finder
Author: Johannes Fischer
Author-email: <aulasparticularesdealemaosp@gmail.com>
License: MIT
Keywords: opencv,cv2,pandas,DataFrame,shapes,object detection,shape
Classifier: Development Status :: 4 - Beta
Classifier: Programming Language :: Python :: 3 :: Only
Classifier: Programming Language :: Python :: 3.9
Classifier: Topic :: Scientific/Engineering :: Visualization
Classifier: Topic :: Software Development :: Libraries :: Python Modules
Classifier: Topic :: Text Editors :: Text Processing
Classifier: Topic :: Text Processing :: General
Classifier: Topic :: Text Processing :: Indexing
Classifier: Topic :: Text Processing :: Filters
Classifier: Topic :: Utilities
License-File: LICENSE.rst
